gecosistema_krige/__init__.py
gecosistema_krige/filesystem.py
gecosistema_krige/krige.py
gecosistema_krige/R/qkrige_v4.1.r
gecosistema_krige/R/qkrige_v4.r
gecosistema_krige-0.0.12.dist-info/METADATA
gecosistema_krige-0.0.12.dist-info/RECORD
gecosistema_krige-0.0.12.dist-info/WHEEL
gecosistema_krige-0.0.12.dist-info/top_level.txt
