Metadata-Version: 2.1
Name: gecosistema-krige
Version: 0.0.12
Summary: A small example package
Home-page: https://github.com/valluzzi/gecosistema_krige.git
Author: Valerio Luzzi
Author-email: valluzzi@gmail.com
License: UNKNOWN
Platform: UNKNOWN
Classifier: Programming Language :: Python :: 2
Classifier: License :: OSI Approved :: MIT License
Classifier: Operating System :: OS Independent
Requires-Dist: gecosistema-core
